salk/__init__.py
salk/bundle.py
salk/rtf2pdf.ps1
salk/tasks.py
salk-0.0.2.dist-info/LICENSE
salk-0.0.2.dist-info/WHEEL
salk-0.0.2.dist-info/METADATA
salk-0.0.2.dist-info/RECORD
