Metadata-Version: 2.1
Name: salk
Version: 0.0.2
Summary: Salk makes reports.
Author-email: hqc47 <abc@123.com>
Classifier: Programming Language :: Python :: 3
Classifier: License :: OSI Approved :: MIT License
Classifier: Operating System :: OS Independent
Requires-Dist: toml
Requires-Dist: fpdf
Requires-Dist: pypdf
Requires-Dist: saspy
